Metadata-Version: 2.1
Name: pyFileSizeUtils
Version: 0.0.2
Summary: File size utils contains method for conversion between size unit like byte, kilobyte, megabyte...
Home-page: https://github.com/xh-dev/pyFileSizeUtils
Author: xethhung
Author-email: pypi@xethh.dev
License: UNKNOWN
Platform: UNKNOWN
Provides-Extra: dev
